mrmatt/__init__.py
mrmatt/__main__.py
mrmatt/mrmatt_game.py
mrmatt/levels/0-empty.png
mrmatt/levels/01 Noisy Bunch.tmx
mrmatt/levels/02 China Store.tmx
mrmatt/levels/03 Lift The Lid.tmx
mrmatt/levels/04 Come again.tmx
mrmatt/levels/1-grass.png
mrmatt/levels/2-wall.png
mrmatt/levels/3-stone.png
mrmatt/levels/4-food.png
mrmatt/levels/5-box1.png
mrmatt/levels/6-box2.png
mrmatt/levels/7-box3.png
mrmatt/levels/8-bomb.png
mrmatt/levels/Die.png
mrmatt/levels/Die.wav
mrmatt/levels/Hero.png
mrmatt/levels/MrMatt.tsx
mrmatt/levels/acorn-mode-1.ttf
mrmatt/levels/app-icon.png
mrmatt/levels/mm_all.wav
mrmatt/levels/mm_bomb.wav
mrmatt/levels/mm_box.wav
mrmatt/levels/mm_champ.wav
mrmatt/levels/mm_debox.wav
mrmatt/levels/mm_error.wav
mrmatt/levels/mm_exit.wav
mrmatt/levels/mm_inp.wav
mrmatt/levels/mm_kill.wav
mrmatt/levels/mm_pick.wav
mrmatt/levels/mm_rest.wav
mrmatt/levels/mm_snap.wav
mrmatt/levels/mm_ston.wav
mrmatt/levels/mm_tada.wav
mrmatt/levels/mm_win.wav
mrmatt/levels/title.png
mrmatt/locale/el/LC_MESSAGES/mrmatt.mo
mrmatt/locale/el/LC_MESSAGES/wincoll.mo
mrmatt/locale/fr/LC_MESSAGES/argparse.mo
mrmatt/locale/fr/LC_MESSAGES/mrmatt.mo
mrmatt/locale/fr/LC_MESSAGES/wincoll.mo
MrMatt-0.8.1.dist-info/METADATA
MrMatt-0.8.1.dist-info/WHEEL
MrMatt-0.8.1.dist-info/entry_points.txt
MrMatt-0.8.1.dist-info/top_level.txt
MrMatt-0.8.1.dist-info/RECORD
