Metadata-Version: 2.2
Name: MrMatt
Version: 0.8.1
Summary: Simple rocks-and-diamonds game
Author-email: Reuben Thomas <rrt@sc3d.org>
License: GPL v3 or later
Project-URL: Homepage, https://github.com/rrthomas/mrmatt
Classifier: Environment :: X11 Applications
Classifier: Environment :: MacOS X
Classifier: Environment :: Win32 (MS Windows)
Classifier: Topic :: Games/Entertainment :: Puzzle Games
Classifier: Programming Language :: Python :: 3
Requires-Python: >=3.12
Requires-Dist: chambercourt>=0.9.18
